discord_eprompt/__init__.py
discord_eprompt-0.3.0.dist-info/LICENSE
discord_eprompt-0.3.0.dist-info/METADATA
discord_eprompt-0.3.0.dist-info/WHEEL
discord_eprompt-0.3.0.dist-info/top_level.txt
discord_eprompt-0.3.0.dist-info/RECORD
